kahi_openalex_subjects/Kahi_openalex_subjects.py
kahi_openalex_subjects/__init__.py
kahi_openalex_subjects/_version.py
Kahi_openalex_subjects-0.1.1b0.dist-info/LICENSE
Kahi_openalex_subjects-0.1.1b0.dist-info/METADATA
Kahi_openalex_subjects-0.1.1b0.dist-info/WHEEL
Kahi_openalex_subjects-0.1.1b0.dist-info/top_level.txt
Kahi_openalex_subjects-0.1.1b0.dist-info/RECORD
