Metadata-Version: 2.1
Name: Kahi_openalex_subjects
Version: 0.1.1b0
Summary: Kahi plugin to insert openalex subjects
Home-page: https://github.com/colav/Kahi_openalex_subjects
Author: Colav
Author-email: colav@udea.edu.co
License: BSD
License-File: LICENSE
Requires-Dist: kahi
Requires-Dist: pymongo
Requires-Dist: joblib
Requires-Dist: datetime
